setup_server.py
common/__init__.py
common/decos.py
common/descriptors.py
common/errors.py
common/metaclasses.py
common/utils.py
common/variables.py
demo_server.egg-info/PKG-INFO
demo_server.egg-info/SOURCES.txt
demo_server.egg-info/dependency_links.txt
demo_server.egg-info/requires.txt
demo_server.egg-info/top_level.txt
logs/__init__.py
logs/config_client_log.py
logs/config_global_log.py
logs/config_server_log.py
server/__init__.py
server/add_user.py
server/config_window.py
server/core.py
server/database_storage.py
server/main_window.py
server/remove_user.py
server/stat_window.py