Metadata-Version: 1.0
Name: demo-server
Version: 0.1.0
Summary: chat_server
Home-page: UNKNOWN
Author: Mr.Windmark
Author-email: agentstorm@ya.ru
License: UNKNOWN
Platform: UNKNOWN
